aiorsmq/__init__.py
aiorsmq/__version__.py
aiorsmq/aiorsmq.py
aiorsmq/compat.py
aiorsmq/exceptions.py
aiorsmq/scripts.py
aiorsmq/utils.py
aiorsmq-0.1.2.dist-info/LICENSE
aiorsmq-0.1.2.dist-info/METADATA
aiorsmq-0.1.2.dist-info/WHEEL
aiorsmq-0.1.2.dist-info/top_level.txt
aiorsmq-0.1.2.dist-info/RECORD
