Metadata-Version: 2.1
Name: aiorsmq
Version: 0.1.2
Summary: Async Python implementation of RSMQ.
Home-page: https://github.com/federicotdn/aiorsmq
Author: Federico Tedin
Author-email: federicotedin@gmail.com
License: UNKNOWN
Download-URL: https://github.com/federicotdn/aiorsmq/archive/refs/tags/0.1.2.zip
Project-URL: Bug Reports, https://github.com/federicotdn/aiorsmq/issues
Keywords: redis,asyncio,async,message,queue,mq
Platform: UNKNOWN
Classifier: Intended Audience :: Developers
Classifier: License :: OSI Approved :: MIT License
Classifier: Programming Language :: Python :: 3
Classifier: Programming Language :: Python :: 3 :: Only
Requires-Python: >=3.6, <4
Requires-Dist: aioredis (<3.0.0,>=2.0.0)
